{"ranks": [{"rating": 29.284693367081275, "name": "Kisuno", "rank": 1}, {"rating": 26.22168222398804, "name": "Aurecia", "rank": 2}, {"rating": 20.624776991363696, "name": "edgekid", "rank": 3}, {"rating": 20.245006920581513, "name": "halfwaycrookk", "rank": 4}, {"rating": 20.21747553127559, "name": "Master_Of_Disaster", "rank": 5}, {"rating": 18.86491245755702, "name": "forsalex", "rank": 6}, {"rating": 15.874205007651051, "name": "RJDollarSign", "rank": 7}, {"rating": 15.329526929021586, "name": "baaliam", "rank": 8}, {"rating": 12.895307648759214, "name": "TheBurntAlmond", "rank": 9}, {"rating": 11.088509216562489, "name": "ICleanWindows", "rank": 10}, {"rating": 10.924252144234906, "name": "Sp0rks", "rank": 11}, {"rating": 9.178809828183233, "name": "llamaq", "rank": 12}, {"rating": 8.835833195702996, "name": "That_0ne_Guy", "rank": 13}, {"rating": 6.6877567453007565, "name": "MrMadPanda", "rank": 14}, {"rating": 6.6877567453007565, "name": "Renzo0", "rank": 15}, {"rating": 5.420287283761809, "name": "MisterGuy24", "rank": 16}, {"rating": 4.54014438379566, "name": "WarMagic", "rank": 17}, {"rating": 4.54014438379566, "name": "VROOM99", "rank": 18}, {"rating": -1.0546579117706543, "name": "Chujji", "rank": 19}, {"rating": -1.0546579117706543, "name": "samkostka", "rank": 20}, {"rating": -1.0546579117706543, "name": "hexacorn", "rank": 21}, {"rating": -1.0944965099994235, "name": "Narross", "rank": 22}, {"rating": -1.650370088824559, "name": "xR_Fox", "rank": 23}, {"rating": -1.650370088824559, "name": "Adwins", "rank": 24}]}